fastapi_docs_exception/__init__.py
fastapi_docs_exception/handler.py
fastapi_docs_exception/py.typed
fastapi_docs_exception-0.4.3.dist-info/METADATA
fastapi_docs_exception-0.4.3.dist-info/WHEEL
fastapi_docs_exception-0.4.3.dist-info/entry_points.txt
fastapi_docs_exception-0.4.3.dist-info/licenses/LICENSE
fastapi_docs_exception-0.4.3.dist-info/RECORD
