Metadata-Version: 2.4
Name: fastapi-docs-exception
Version: 0.4.3
Summary: Add your description here
Author-email: Athroniaeth <pierre.chaumont@hotmail.fr>
License-File: LICENSE
Classifier: Framework :: FastAPI
Classifier: Intended Audience :: Developers
Classifier: License :: OSI Approved :: MIT License
Classifier: Programming Language :: Python :: 3 :: Only
Classifier: Programming Language :: Python :: 3.8
Classifier: Programming Language :: Python :: 3.9
Classifier: Programming Language :: Python :: 3.10
Classifier: Programming Language :: Python :: 3.11
Classifier: Programming Language :: Python :: 3.12
Classifier: Programming Language :: Python :: 3.13
Classifier: Topic :: Documentation
Requires-Python: >=3.8
